[{"url": "http://www.klinikbewertungen.de/klinik-forum/erfahrung-mit-st-martinus-krankenhaus-duesseldorf/bewertungen?allbew#more", "datum": "02.06.2015", "id_plattform": 1, "kommentar": "Ich bin von Freitag 29.05.15 bis heute Dienstag 02.06.15 im St.Martinus Krankenhaus Abteilung 04 als Patientin gewesen. Da ich schon in vielen anderen Krankenh\u00e4usern war, muss ich sagen, ich hatte noch niemals einen solch angenehmen Aufenthalt in einer Klinik. Es gab nichts, aber auch garnichts zu beanstanden.\u00c4rzte, Personal, Zimmer, Essen usw. waren Klasse. Der Aufenthalt dort war super.Ich w\u00fcnsche allen Angestellten und \u00c4rzten, das sie so weitermachen."},
{"url": "http://www.klinikbewertungen.de/klinik-forum/erfahrung-mit-st-martinus-krankenhaus-duesseldorf/bewertungen?allbew#more", "datum": "11.06.2015", "id_plattform": 1, "kommentar": "Ich bin sehr begeistert von diesem Krankenhaus. Das kompetente "Team" (\u00c4rzte, Krankenschwestern und Pflegern) sind sehr nett und freundlich. Es ist ein sauberes und gepflegtes Haus mit einer sehr angenehmen Atmosph\u00E4re. Ich habe mich dort als Kassenpatient 9 Tage lang sehr wohl gef\u00FChlt und kann dieses Haus sehr empfehlen. Meinen herzlichen Dank an das gesamte Team, komme gerne wieder wenn es von N\u00F6ten sein sollte."}]